[
  {
    "timestamp": "2025-06-06T12:06:25.890Z",
    "type": "character",
    "name": "ava",
    "mood": "surprised",
    "filename": "ava_surprised.png",
    "path": "resources/characters/ava_surprised.png"
  },
  {
    "timestamp": "2025-06-06T12:22:36.861Z",
    "type": "character",
    "name": "ava",
    "mood": "flustered",
    "filename": "ava_flustered.png",
    "path": "resources/characters/ava_flustered.png"
  },
  {
    "timestamp": "2025-06-06T13:18:07.112Z",
    "type": "background",
    "name": "secluded cove",
    "filename": "secluded cove.png",
    "path": "resources/backgrounds/secluded cove.png"
  }
]